README.rst
async_retrying.py
setup.py
async_retrying.egg-info/PKG-INFO
async_retrying.egg-info/SOURCES.txt
async_retrying.egg-info/dependency_links.txt
async_retrying.egg-info/not-zip-safe
async_retrying.egg-info/requires.txt
async_retrying.egg-info/top_level.txt