Metadata-Version: 1.1
Name: async-retrying
Version: 0.2.1
Summary: Simple retrying for asyncio
Home-page: https://github.com/wikibusiness/async_retrying
Author: OCEAN S.A.
Author-email: osf@ocean.io
License: UNKNOWN
Keywords: asyncio,retrying
Platform: UNKNOWN
Classifier: Development Status :: 4 - Beta
Classifier: Intended Audience :: Developers
Classifier: License :: OSI Approved :: MIT License
Classifier: Programming Language :: Python
Classifier: Programming Language :: Python :: 3
Classifier: Programming Language :: Python :: 3.3
Classifier: Programming Language :: Python :: 3.4
Classifier: Programming Language :: Python :: 3.5
Classifier: Programming Language :: Python :: 3.6
